{
    "event": "suiteStart",
    "suite": "WSC_frame",
    "tests": 24
}{
    "event": "suiteStart",
    "suite": "WSC\\UnitTests\\testBootstrap",
    "tests": 24
}{
    "event": "suiteStart",
    "suite": "WSC\\UnitTests\\testBootstrap::test_viewport",
    "tests": 24
}{
    "event": "testStart",
    "suite": "WSC\\UnitTests\\testBootstrap::test_viewport",
    "test": "WSC\\UnitTests\\testBootstrap::test_viewport with data set #0 (array(null, null, null, null, null, null), 'error')"
}{
    "event": "test",
    "suite": "WSC\\UnitTests\\testBootstrap::test_viewport",
    "test": "WSC\\UnitTests\\testBootstrap::test_viewport with data set #0 (array(null, null, null, null, null, null), 'error')",
    "status": "pass",
    "time": 0.0039999485015869,
    "trace": [],
    "message": "",
    "output": ""
}{
    "event": "testStart",
    "suite": "WSC\\UnitTests\\testBootstrap::test_viewport",
    "test": "WSC\\UnitTests\\testBootstrap::test_viewport with data set #1 (array('device-width', null, null, null, null, null), '<meta name=\"viewport\" content...idth\">')"
}{
    "event": "test",
    "suite": "WSC\\UnitTests\\testBootstrap::test_viewport",
    "test": "WSC\\UnitTests\\testBootstrap::test_viewport with data set #1 (array('device-width', null, null, null, null, null), '<meta name=\"viewport\" content...idth\">')",
    "status": "pass",
    "time": 0.003000020980835,
    "trace": [],
    "message": "",
    "output": ""
}{
    "event": "testStart",
    "suite": "WSC\\UnitTests\\testBootstrap::test_viewport",
    "test": "WSC\\UnitTests\\testBootstrap::test_viewport with data set #2 (array(null, 'device-height', null, null, null, null), '<meta name=\"viewport\" content...ight\">')"
}{
    "event": "test",
    "suite": "WSC\\UnitTests\\testBootstrap::test_viewport",
    "test": "WSC\\UnitTests\\testBootstrap::test_viewport with data set #2 (array(null, 'device-height', null, null, null, null), '<meta name=\"viewport\" content...ight\">')",
    "status": "pass",
    "time": 0.003000020980835,
    "trace": [],
    "message": "",
    "output": ""
}{
    "event": "testStart",
    "suite": "WSC\\UnitTests\\testBootstrap::test_viewport",
    "test": "WSC\\UnitTests\\testBootstrap::test_viewport with data set #3 (array(null, null, 1, null, null, null), '<meta name=\"viewport\" content...le=1\">')"
}{
    "event": "test",
    "suite": "WSC\\UnitTests\\testBootstrap::test_viewport",
    "test": "WSC\\UnitTests\\testBootstrap::test_viewport with data set #3 (array(null, null, 1, null, null, null), '<meta name=\"viewport\" content...le=1\">')",
    "status": "pass",
    "time": 0.003000020980835,
    "trace": [],
    "message": "",
    "output": ""
}{
    "event": "testStart",
    "suite": "WSC\\UnitTests\\testBootstrap::test_viewport",
    "test": "WSC\\UnitTests\\testBootstrap::test_viewport with data set #4 (array(null, null, null, 1, null, null), '<meta name=\"viewport\" content...le=1\">')"
}{
    "event": "test",
    "suite": "WSC\\UnitTests\\testBootstrap::test_viewport",
    "test": "WSC\\UnitTests\\testBootstrap::test_viewport with data set #4 (array(null, null, null, 1, null, null), '<meta name=\"viewport\" content...le=1\">')",
    "status": "pass",
    "time": 0.0020010471343994,
    "trace": [],
    "message": "",
    "output": ""
}{
    "event": "testStart",
    "suite": "WSC\\UnitTests\\testBootstrap::test_viewport",
    "test": "WSC\\UnitTests\\testBootstrap::test_viewport with data set #5 (array(null, null, null, null, 1, null), '<meta name=\"viewport\" content...le=1\">')"
}{
    "event": "test",
    "suite": "WSC\\UnitTests\\testBootstrap::test_viewport",
    "test": "WSC\\UnitTests\\testBootstrap::test_viewport with data set #5 (array(null, null, null, null, 1, null), '<meta name=\"viewport\" content...le=1\">')",
    "status": "pass",
    "time": 0.0049998760223389,
    "trace": [],
    "message": "",
    "output": ""
}{
    "event": "testStart",
    "suite": "WSC\\UnitTests\\testBootstrap::test_viewport",
    "test": "WSC\\UnitTests\\testBootstrap::test_viewport with data set #6 (array(null, null, null, null, 2, null), '<meta name=\"viewport\" content...le=2\">')"
}{
    "event": "test",
    "suite": "WSC\\UnitTests\\testBootstrap::test_viewport",
    "test": "WSC\\UnitTests\\testBootstrap::test_viewport with data set #6 (array(null, null, null, null, 2, null), '<meta name=\"viewport\" content...le=2\">')",
    "status": "pass",
    "time": 0.0030009746551514,
    "trace": [],
    "message": "",
    "output": ""
}{
    "event": "testStart",
    "suite": "WSC\\UnitTests\\testBootstrap::test_viewport",
    "test": "WSC\\UnitTests\\testBootstrap::test_viewport with data set #7 (array(null, null, null, null, null, 'no'), '<meta name=\"viewport\" content...e=no\">')"
}{
    "event": "test",
    "suite": "WSC\\UnitTests\\testBootstrap::test_viewport",
    "test": "WSC\\UnitTests\\testBootstrap::test_viewport with data set #7 (array(null, null, null, null, null, 'no'), '<meta name=\"viewport\" content...e=no\">')",
    "status": "pass",
    "time": 0.003000020980835,
    "trace": [],
    "message": "",
    "output": ""
}{
    "event": "testStart",
    "suite": "WSC\\UnitTests\\testBootstrap::test_viewport",
    "test": "WSC\\UnitTests\\testBootstrap::test_viewport with data set #8 (array(null, null, null, null, null, 'yes'), '<meta name=\"viewport\" content...=yes\">')"
}{
    "event": "test",
    "suite": "WSC\\UnitTests\\testBootstrap::test_viewport",
    "test": "WSC\\UnitTests\\testBootstrap::test_viewport with data set #8 (array(null, null, null, null, null, 'yes'), '<meta name=\"viewport\" content...=yes\">')",
    "status": "pass",
    "time": 0.003000020980835,
    "trace": [],
    "message": "",
    "output": ""
}{
    "event": "testStart",
    "suite": "WSC\\UnitTests\\testBootstrap::test_viewport",
    "test": "WSC\\UnitTests\\testBootstrap::test_viewport with data set #9 (array('device-width', 'device-height', null, null, null, null), '<meta name=\"viewport\" content...ight\">')"
}{
    "event": "test",
    "suite": "WSC\\UnitTests\\testBootstrap::test_viewport",
    "test": "WSC\\UnitTests\\testBootstrap::test_viewport with data set #9 (array('device-width', 'device-height', null, null, null, null), '<meta name=\"viewport\" content...ight\">')",
    "status": "pass",
    "time": 0.0039999485015869,
    "trace": [],
    "message": "",
    "output": ""
}{
    "event": "testStart",
    "suite": "WSC\\UnitTests\\testBootstrap::test_viewport",
    "test": "WSC\\UnitTests\\testBootstrap::test_viewport with data set #10 (array('device-width', null, 1, null, null, null), '<meta name=\"viewport\" content...le=1\">')"
}{
    "event": "test",
    "suite": "WSC\\UnitTests\\testBootstrap::test_viewport",
    "test": "WSC\\UnitTests\\testBootstrap::test_viewport with data set #10 (array('device-width', null, 1, null, null, null), '<meta name=\"viewport\" content...le=1\">')",
    "status": "pass",
    "time": 0.0040011405944824,
    "trace": [],
    "message": "",
    "output": ""
}{
    "event": "testStart",
    "suite": "WSC\\UnitTests\\testBootstrap::test_viewport",
    "test": "WSC\\UnitTests\\testBootstrap::test_viewport with data set #11 (array('device-width', null, 1.5, null, null, null), '<meta name=\"viewport\" content...=1.5\">')"
}{
    "event": "test",
    "suite": "WSC\\UnitTests\\testBootstrap::test_viewport",
    "test": "WSC\\UnitTests\\testBootstrap::test_viewport with data set #11 (array('device-width', null, 1.5, null, null, null), '<meta name=\"viewport\" content...=1.5\">')",
    "status": "pass",
    "time": 0.003000020980835,
    "trace": [],
    "message": "",
    "output": ""
}{
    "event": "testStart",
    "suite": "WSC\\UnitTests\\testBootstrap::test_viewport",
    "test": "WSC\\UnitTests\\testBootstrap::test_viewport with data set #12 (array('device-width', null, 2, null, null, null), '<meta name=\"viewport\" content...le=2\">')"
}{
    "event": "test",
    "suite": "WSC\\UnitTests\\testBootstrap::test_viewport",
    "test": "WSC\\UnitTests\\testBootstrap::test_viewport with data set #12 (array('device-width', null, 2, null, null, null), '<meta name=\"viewport\" content...le=2\">')",
    "status": "pass",
    "time": 0.003000020980835,
    "trace": [],
    "message": "",
    "output": ""
}{
    "event": "testStart",
    "suite": "WSC\\UnitTests\\testBootstrap::test_viewport",
    "test": "WSC\\UnitTests\\testBootstrap::test_viewport with data set #13 (array('device-width', null, null, 1, null, null), '<meta name=\"viewport\" content...le=1\">')"
}{
    "event": "test",
    "suite": "WSC\\UnitTests\\testBootstrap::test_viewport",
    "test": "WSC\\UnitTests\\testBootstrap::test_viewport with data set #13 (array('device-width', null, null, 1, null, null), '<meta name=\"viewport\" content...le=1\">')",
    "status": "pass",
    "time": 0.003000020980835,
    "trace": [],
    "message": "",
    "output": ""
}{
    "event": "testStart",
    "suite": "WSC\\UnitTests\\testBootstrap::test_viewport",
    "test": "WSC\\UnitTests\\testBootstrap::test_viewport with data set #14 (array('device-width', null, null, 2, null, null), '<meta name=\"viewport\" content...le=2\">')"
}{
    "event": "test",
    "suite": "WSC\\UnitTests\\testBootstrap::test_viewport",
    "test": "WSC\\UnitTests\\testBootstrap::test_viewport with data set #14 (array('device-width', null, null, 2, null, null), '<meta name=\"viewport\" content...le=2\">')",
    "status": "pass",
    "time": 0.003000020980835,
    "trace": [],
    "message": "",
    "output": ""
}{
    "event": "testStart",
    "suite": "WSC\\UnitTests\\testBootstrap::test_viewport",
    "test": "WSC\\UnitTests\\testBootstrap::test_viewport with data set #15 (array('device-width', null, null, 1, 1, null), '<meta name=\"viewport\" content...le=1\">')"
}{
    "event": "test",
    "suite": "WSC\\UnitTests\\testBootstrap::test_viewport",
    "test": "WSC\\UnitTests\\testBootstrap::test_viewport with data set #15 (array('device-width', null, null, 1, 1, null), '<meta name=\"viewport\" content...le=1\">')",
    "status": "pass",
    "time": 0.0019998550415039,
    "trace": [],
    "message": "",
    "output": ""
}{
    "event": "testStart",
    "suite": "WSC\\UnitTests\\testBootstrap::test_viewport",
    "test": "WSC\\UnitTests\\testBootstrap::test_viewport with data set #16 (array('device-width', null, null, 1, 2, null), '<meta name=\"viewport\" content...le=2\">')"
}{
    "event": "test",
    "suite": "WSC\\UnitTests\\testBootstrap::test_viewport",
    "test": "WSC\\UnitTests\\testBootstrap::test_viewport with data set #16 (array('device-width', null, null, 1, 2, null), '<meta name=\"viewport\" content...le=2\">')",
    "status": "pass",
    "time": 0.0040009021759033,
    "trace": [],
    "message": "",
    "output": ""
}{
    "event": "testStart",
    "suite": "WSC\\UnitTests\\testBootstrap::test_viewport",
    "test": "WSC\\UnitTests\\testBootstrap::test_viewport with data set #17 (array('device-width', null, null, 1, 1, 'no'), '<meta name=\"viewport\" content...e=no\">')"
}{
    "event": "test",
    "suite": "WSC\\UnitTests\\testBootstrap::test_viewport",
    "test": "WSC\\UnitTests\\testBootstrap::test_viewport with data set #17 (array('device-width', null, null, 1, 1, 'no'), '<meta name=\"viewport\" content...e=no\">')",
    "status": "pass",
    "time": 0.0039999485015869,
    "trace": [],
    "message": "",
    "output": ""
}{
    "event": "testStart",
    "suite": "WSC\\UnitTests\\testBootstrap::test_viewport",
    "test": "WSC\\UnitTests\\testBootstrap::test_viewport with data set #18 (array('device-width', null, null, 1, 1, 'yes'), '<meta name=\"viewport\" content...=yes\">')"
}{
    "event": "test",
    "suite": "WSC\\UnitTests\\testBootstrap::test_viewport",
    "test": "WSC\\UnitTests\\testBootstrap::test_viewport with data set #18 (array('device-width', null, null, 1, 1, 'yes'), '<meta name=\"viewport\" content...=yes\">')",
    "status": "pass",
    "time": 0.0040011405944824,
    "trace": [],
    "message": "",
    "output": ""
}{
    "event": "testStart",
    "suite": "WSC\\UnitTests\\testBootstrap::test_viewport",
    "test": "WSC\\UnitTests\\testBootstrap::test_viewport with data set #19 (array('device-width', null, null, null, 1, 'no'), '<meta name=\"viewport\" content...e=no\">')"
}{
    "event": "test",
    "suite": "WSC\\UnitTests\\testBootstrap::test_viewport",
    "test": "WSC\\UnitTests\\testBootstrap::test_viewport with data set #19 (array('device-width', null, null, null, 1, 'no'), '<meta name=\"viewport\" content...e=no\">')",
    "status": "pass",
    "time": 0.003000020980835,
    "trace": [],
    "message": "",
    "output": ""
}{
    "event": "testStart",
    "suite": "WSC\\UnitTests\\testBootstrap::test_viewport",
    "test": "WSC\\UnitTests\\testBootstrap::test_viewport with data set #20 (array('device-width', null, null, null, 1, 'yes'), '<meta name=\"viewport\" content...=yes\">')"
}{
    "event": "test",
    "suite": "WSC\\UnitTests\\testBootstrap::test_viewport",
    "test": "WSC\\UnitTests\\testBootstrap::test_viewport with data set #20 (array('device-width', null, null, null, 1, 'yes'), '<meta name=\"viewport\" content...=yes\">')",
    "status": "pass",
    "time": 0.0040011405944824,
    "trace": [],
    "message": "",
    "output": ""
}{
    "event": "testStart",
    "suite": "WSC\\UnitTests\\testBootstrap::test_viewport",
    "test": "WSC\\UnitTests\\testBootstrap::test_viewport with data set #21 (array('device-width', null, null, null, null, 'no'), '<meta name=\"viewport\" content...e=no\">')"
}{
    "event": "test",
    "suite": "WSC\\UnitTests\\testBootstrap::test_viewport",
    "test": "WSC\\UnitTests\\testBootstrap::test_viewport with data set #21 (array('device-width', null, null, null, null, 'no'), '<meta name=\"viewport\" content...e=no\">')",
    "status": "pass",
    "time": 0.0049998760223389,
    "trace": [],
    "message": "",
    "output": ""
}{
    "event": "testStart",
    "suite": "WSC\\UnitTests\\testBootstrap::test_viewport",
    "test": "WSC\\UnitTests\\testBootstrap::test_viewport with data set #22 (array('device-width', null, null, null, null, 'yes'), '<meta name=\"viewport\" content...=yes\">')"
}{
    "event": "test",
    "suite": "WSC\\UnitTests\\testBootstrap::test_viewport",
    "test": "WSC\\UnitTests\\testBootstrap::test_viewport with data set #22 (array('device-width', null, null, null, null, 'yes'), '<meta name=\"viewport\" content...=yes\">')",
    "status": "pass",
    "time": 0.003000020980835,
    "trace": [],
    "message": "",
    "output": ""
}{
    "event": "testStart",
    "suite": "WSC\\UnitTests\\testBootstrap::test_viewport",
    "test": "WSC\\UnitTests\\testBootstrap::test_viewport with data set #23 ('', '<meta name=\"viewport\" content...=yes\">')"
}{
    "event": "test",
    "suite": "WSC\\UnitTests\\testBootstrap::test_viewport",
    "test": "WSC\\UnitTests\\testBootstrap::test_viewport with data set #23 ('', '<meta name=\"viewport\" content...=yes\">')",
    "status": "error",
    "time": 0.0060000419616699,
    "trace": [
        {
            "file": "C:\\xampp\\htdocs\\lib\\wsc_Framework\\bootstrap.class.php",
            "line": 43,
            "function": "array_filter"
        },
        {
            "file": "C:\\xampp\\htdocs\\lib\\wsc_Framework\\tests\\bootstrap.test.php",
            "line": 307,
            "function": "viewport",
            "class": "WSC\\Framework\\Assemblers\\Bootstrap",
            "type": "->"
        },
        {
            "file": "C:\\xampp\\php\\pear\\PHPUnit\\TextUI\\Command.php",
            "line": 176,
            "function": "doRun",
            "class": "PHPUnit_TextUI_TestRunner",
            "type": "->"
        },
        {
            "file": "C:\\xampp\\php\\pear\\PHPUnit\\TextUI\\Command.php",
            "line": 129,
            "function": "run",
            "class": "PHPUnit_TextUI_Command",
            "type": "->"
        }
    ],
    "message": "array_filter() expects parameter 1 to be array, string given",
    "output": ""
}